avh_api_async/__init__.py
avh_api_async/api_client.py
avh_api_async/configuration.py
avh_api_async/exceptions.py
avh_api_async/rest.py
avh_api_async/api/__init__.py
avh_api_async/api/arm_api.py
avh_api_async/models/__init__.py
avh_api_async/models/address.py
avh_api_async/models/agent_app.py
avh_api_async/models/agent_app_ready_response.py
avh_api_async/models/agent_app_status.py
avh_api_async/models/agent_apps_list.py
avh_api_async/models/agent_apps_status_list.py
avh_api_async/models/agent_error.py
avh_api_async/models/agent_icons.py
avh_api_async/models/agent_install_body.py
avh_api_async/models/agent_profiles_return.py
avh_api_async/models/agent_system_adb_auth.py
avh_api_async/models/agent_system_get_prop_body.py
avh_api_async/models/agent_value_return.py
avh_api_async/models/agreed_ack.py
avh_api_async/models/api_conflict_error.py
avh_api_async/models/api_error.py
avh_api_async/models/api_internal_consistency_error.py
avh_api_async/models/api_not_found_error.py
avh_api_async/models/api_token.py
avh_api_async/models/bit.py
avh_api_async/models/btrace_enable_options.py
avh_api_async/models/button.py
avh_api_async/models/coupon_options.py
avh_api_async/models/create_team.py
avh_api_async/models/created_by.py
avh_api_async/models/credentials.py
avh_api_async/models/domain_options.py
avh_api_async/models/extension.py
avh_api_async/models/features.py
avh_api_async/models/file_changes.py
avh_api_async/models/firmware.py
avh_api_async/models/gpio_state_definition.py
avh_api_async/models/gpios_state.py
avh_api_async/models/grant_trial_request_response.py
avh_api_async/models/hook.py
avh_api_async/models/image.py
avh_api_async/models/instance.py
avh_api_async/models/instance_agent_state.py
avh_api_async/models/instance_boot_options.py
avh_api_async/models/instance_boot_options_additional_tag.py
avh_api_async/models/instance_console_endpoint.py
avh_api_async/models/instance_create_options.py
avh_api_async/models/instance_input.py
avh_api_async-1.0.3.dist-info/METADATA
avh_api_async-1.0.3.dist-info/WHEEL
avh_api_async-1.0.3.dist-info/top_level.txt
avh_api_async-1.0.3.dist-info/RECORD
